{"cameraMode":{"drawMode":0,"name":"Shaded","section":"Shading Mode"},"sceneLighting":true,"audioPlay":false,"sceneViewState":{"m_AlwaysRefresh":false,"showFog":true,"showSkybox":true,"showFlares":true,"showImageEffects":true,"showParticleSystems":true,"showVisualEffectGraphs":true,"m_FxEnabled":true},"in2DMode":false,"pivot":{"x":402.37738037109377,"y":43.370365142822269,"z":76.60267639160156},"rotation":{"x":0.14812220633029939,"y":-0.8028953671455383,"z":0.22333984076976777,"w":0.5324883460998535},"size":1.6383308172225953,"orthographic":false}